yw_gw_sdk/__init__.py
yw_gw_sdk/conf_parser.py
yw_gw_sdk/exception.py
yw_gw_sdk/request.py
yw_gw_sdk/signer.py
yw_gw_sdk/test.py
yw_gw_sdk-0.0.5.dist-info/METADATA
yw_gw_sdk-0.0.5.dist-info/WHEEL
yw_gw_sdk-0.0.5.dist-info/top_level.txt
yw_gw_sdk-0.0.5.dist-info/RECORD
